aparatCrawler/__init__.py
aparatCrawler/firstPageFetcher.py
aparatCrawler/getChanneldetails.py
aparatCrawler/getOfficialChannels.py
aparatCrawler/getVideoRecommndedChannles.py
aparatCrawler/getVideodetails.py
aparatCrawler/getVideodetails_OLD.py
aparatCrawler/getchaneelVideosDetail.py
aparatCrawler/getchaneelVideosuid.py
aparatCrawler/search.py
aparat_crawler-0.9.1.9.4.dist-info/LICENSE
aparat_crawler-0.9.1.9.4.dist-info/METADATA
aparat_crawler-0.9.1.9.4.dist-info/WHEEL
aparat_crawler-0.9.1.9.4.dist-info/top_level.txt
aparat_crawler-0.9.1.9.4.dist-info/RECORD
