Metadata-Version: 2.1
Name: aparat_crawler
Version: 0.9.1.9.4
Summary: this is an aparat crawler library
Home-page: https://github.com/maorojloo/aparat_crawler
Author: Mohammad Amin Orojloo
Author-email: ma.orojloo@gmail.com
Classifier: Programming Language :: Python :: 3.10
License-File: LICENSE
Requires-Dist: beautifulsoup4 ==4.12.3
Requires-Dist: persian ==0.5.0
Requires-Dist: requests ==2.31.0
Requires-Dist: aiohttp ==3.8.6
Requires-Dist: aiohttp-socks ==0.8.4
